malac/hd/__init__.py
malac/hd/__main__.py
malac/hd/build.py
malac/hd/core/__init__.py
malac/hd/core/fhir/__init__.py
malac/hd/core/fhir/base/__init__.py
malac/hd/core/fhir/base/generator/__init__.py
malac/hd/core/fhir/base/generator/fhirpath.py
malac/hd/core/fhir/base/generator/fml.py
malac/hd/core/fhir/base/generator/resource.py
malac/hd/core/fhir/base/parser/__init__.py
malac/hd/core/fhir/base/parser/fhirpath.g4
malac/hd/core/fhir/base/parser/fhirpath.interp
malac/hd/core/fhir/base/parser/fhirpath.tokens
malac/hd/core/fhir/base/parser/fhirpathLexer.interp
malac/hd/core/fhir/base/parser/fhirpathLexer.py
malac/hd/core/fhir/base/parser/fhirpathLexer.tokens
malac/hd/core/fhir/base/parser/fhirpathListener.py
malac/hd/core/fhir/base/parser/fhirpathParser.py
malac/hd/core/fhir/r4/__init__.py
malac/hd/core/fhir/r4/generator/__init__.py
malac/hd/core/fhir/r4/generator/conceptmap.py
malac/hd/core/fhir/r4/generator/fhirpath.py
malac/hd/core/fhir/r4/generator/fml.py
malac/hd/core/fhir/r4/generator/structuremap.py
malac/hd/core/fhir/r4/parser/__init__.py
malac/hd/core/fhir/r4/parser/fhirpath.g4
malac/hd/core/fhir/r4/parser/mapping.g4
malac/hd/core/fhir/r4/parser/mapping.interp
malac/hd/core/fhir/r4/parser/mapping.tokens
malac/hd/core/fhir/r4/parser/mappingLexer.interp
malac/hd/core/fhir/r4/parser/mappingLexer.py
malac/hd/core/fhir/r4/parser/mappingLexer.tokens
malac/hd/core/fhir/r4/parser/mappingListener.py
malac/hd/core/fhir/r4/parser/mappingParser.py
malac/hd/core/fhir/r5/__init__.py
malac/hd/core/fhir/r5/generator/__init__.py
malac/hd/core/fhir/r5/generator/conceptmap.py
malac/hd/core/fhir/r5/generator/fhirpath.py
malac/hd/core/fhir/r5/generator/fml.py
malac/hd/core/fhir/r5/generator/structuredefinition.py
malac/hd/core/fhir/r5/generator/structuremap.py
malac/hd/core/fhir/r5/parser/__init__.py
malac/hd/core/fhir/r5/parser/fhirpath.g4
malac/hd/core/fhir/r5/parser/mapping.g4
malac/hd/core/fhir/r5/parser/mapping.interp
malac/hd/core/fhir/r5/parser/mapping.tokens
malac_hd-1.2.0.dist-info/LICENSE
malac_hd-1.2.0.dist-info/METADATA
malac_hd-1.2.0.dist-info/WHEEL
malac_hd-1.2.0.dist-info/entry_points.txt
malac_hd-1.2.0.dist-info/top_level.txt
malac_hd-1.2.0.dist-info/RECORD
