Metadata-Version: 2.1
Name: malac-hd
Version: 1.2.0
Summary: Mapping Language Compiler for Health Data.
Author-email: cdeHealth-Team <contact-project+cdehealth-malac-hd-52276676-issue-@incoming.gitlab.com>
Project-URL: Homepage, https://gitlab.com/cdehealth/malac-hd
Project-URL: Documentation, https://gitlab.com/cdehealth/malac-hd
Project-URL: Release notes, https://gitlab.com/cdehealth/malac-hd/-/releases
Project-URL: Source, https://gitlab.com/cdehealth/malac-hd
Project-URL: Tracker, https://gitlab.com/cdehealth/malac-hd/-/issues
Classifier: Development Status :: 5 - Production/Stable
Classifier: Environment :: Console
Classifier: Intended Audience :: Information Technology
Classifier: Intended Audience :: Healthcare Industry
Classifier: Intended Audience :: Developers
Classifier: Intended Audience :: Science/Research
Classifier: License :: OSI Approved :: GNU Lesser General Public License v3 (LGPLv3)
Classifier: Natural Language :: English
Classifier: Operating System :: OS Independent
Classifier: Programming Language :: Python
Classifier: Topic :: Software Development :: Code Generators
Classifier: Topic :: Software Development :: Libraries
Requires-Python: >=3.10
License-File: LICENSE
Requires-Dist: malac-utils>=1.2.0
Requires-Dist: malac-models-fhir>=1.1.0
Requires-Dist: malac-models-cda>=1.1.0
Requires-Dist: malac-transformer-fhir>=1.1.0
Requires-Dist: antlr4-python3-runtime>=4.13.0
Requires-Dist: antlr4-tools>=0.2.1
Provides-Extra: cda
Requires-Dist: malac-models-cda>=1.1.0; extra == "cda"
Provides-Extra: test
Requires-Dist: pytest>=7.0.0; extra == "test"
